{
  "groups": [
    {
      "group_number": 1,
      "members": [
        "김시완",
        "임지안",
        "박유안",
        "유소유",
        "박예희",
        "김시은",
        "박보영"
      ]
    },
    {
      "group_number": 2,
      "members": [
        "김강민",
        "김휘연",
        "김예율",
        "허하은",
        "김은율",
        "변진솔",
        "양서진"
      ]
    },
    {
      "group_number": 3,
      "members": ["손하준", "김지훈", "정시우", "최서연", "한가은", "이유민"]
    },
    {
      "group_number": 4,
      "members": [
        "박주언",
        "신동혁",
        "권유하",
        "고은우",
        "조은성",
        "유하린",
        "이하엘"
      ]
    },
    {
      "group_number": 5,
      "members": [
        "우지온",
        "박이레",
        "이준",
        "장민하",
        "이사랑",
        "신윤서",
        "이서현"
      ]
    },
    {
      "group_number": 6,
      "members": ["오크리스", "조아인", "윤준영", "하민지", "남지우", "강수아"]
    },
    {
      "group_number": 7,
      "members": [
        "지승민",
        "최도윤",
        "양서훈",
        "김도언",
        "유하은",
        "김라희",
        "김하진"
      ]
    },
    {
      "group_number": 8,
      "members": ["박준후", "박승우", "유이룸", "이시후", "신하은", "나연재"]
    },
    {
      "group_number": 9,
      "members": [
        "차은우",
        "신이안",
        "백하담",
        "강예준",
        "박승원",
        "이서진",
        "최래인"
      ]
    },
    {
      "group_number": 10,
      "members": [
        "엄유하",
        "한준희",
        "이루신",
        "이유진",
        "김주아",
        "이지아",
        "강다인"
      ]
    },
    {
      "group_number": 11,
      "members": [
        "박시우",
        "노서우",
        "주예랑",
        "임지섭",
        "이수영",
        "박서은",
        "명라언",
        "이은후",
        "편주원"
      ]
    },
    {
      "group_number": 12,
      "members": [
        "김정연",
        "곽명호",
        "장연후",
        "이로희",
        "김민유",
        "김지안",
        "박가영",
        "안지현",
        "조서하"
      ]
    },
    {
      "group_number": 13,
      "members": [
        "임해성",
        "홍서휘",
        "이선율",
        "서재후",
        "김건우",
        "이진하",
        "박사랑",
        "이반희",
        "민채아"
      ]
    },
    {
      "group_number": 14,
      "members": [
        "원찬영",
        "김도헌",
        "김루아",
        "현유빈",
        "문서하",
        "주수빈",
        "김한별",
        "황지인",
        "이수빈"
      ]
    },
    {
      "group_number": 15,
      "members": [
        "홍이안",
        "이온유",
        "최정우",
        "신재형",
        "변하영",
        "조아영",
        "김하임",
        "박서빈",
        "이하율"
      ]
    },
    {
      "group_number": 16,
      "members": [
        "박준후",
        "권일우",
        "조우빈",
        "이소희",
        "이온유",
        "곽다은",
        "김하온",
        "이예빈",
        "최이룸"
      ]
    },
    {
      "group_number": 17,
      "members": [
        "라하준",
        "이윤재",
        "정지온",
        "안휘준",
        "신지유",
        "서예은",
        "김소윤",
        "조이레",
        "조이루"
      ]
    },
    {
      "group_number": 18,
      "members": [
        "이하준",
        "이하진",
        "정하은",
        "최서현",
        "이채원",
        "송리아",
        "김조이",
        "유은선",
        "정한나"
      ]
    },
    {
      "group_number": 19,
      "members": [
        "박건률",
        "서민찬",
        "김지안",
        "김선민",
        "한예은",
        "신윤서",
        "이라율",
        "박세미",
        "성라희"
      ]
    },
    {
      "group_number": 20,
      "members": [
        "이시우",
        "김민찬",
        "김진우",
        "강시은",
        "김하음",
        "최아인",
        "유진서",
        "김유경",
        "최효진",
        "최예승"
      ]
    }
  ]
}
